rust_itertools-0.0.1.dist-info/METADATA
rust_itertools-0.0.1.dist-info/WHEEL
rust_itertools-0.0.1.dist-info/licenses/LICENSE
rust_itertools/_rust_itertools.pyi
rust_itertools/__init__.py
rust_itertools/py.typed
rust_itertools/_rust_itertools.abi3.so
rust_itertools-0.0.1.dist-info/RECORD
