Metadata-Version: 2.4
Name: rust_itertools
Version: 0.0.1
Classifier: Programming Language :: Python :: 3
Classifier: License :: OSI Approved :: MIT License
Classifier: Operating System :: OS Independent
Requires-Dist: more-itertools >=10.5.0
Requires-Dist: pytest >=8.3.4
License-File: LICENSE
Summary: Run Rusts itertools and more in Python.
Keywords: itertools
Author: Bert de Bruijn
Author-email: Bert de Bruijn <lpdebruijn@gmail.com>
License: MIT
Requires-Python: >=3.10
Project-URL: Homepage, https://gitlab.com/bert.debruijn/rust_itertools
Project-URL: Issues, https://gitlab.com/bert.debruijn/rust_itertools/-/issues
